chateval/__init__.py
chateval/chateval.py
chateval/config.py
chateval/load.py
chateval/constants/__init__.py
chateval/constants/models.py
chateval/kernels/__init__.py
chateval/kernels/kernel.py
chateval/kernels/openai.py
chateval/kernels/openai_test.py
chateval/metrics/__init__.py
chateval/metrics/accuracy.py
chateval/metrics/count.py
chateval/metrics/gptscore.py
chateval/metrics/metric.py
chateval/metrics/rouge.py
chateval/metrics/protocols/__init__.py
chateval/metrics/protocols/blenderbot2_bool.yaml
chateval/metrics/protocols/debate_overall.yaml
chateval/metrics/protocols/generic_bool.yaml
chateval/metrics/protocols/generic_bool_safety.yaml
chateval/metrics/protocols/generic_likert.yaml
chateval/metrics/protocols/generic_pairwise.yaml
chateval/metrics/protocols/generic_rank.yaml
chateval/metrics/protocols/lima_pairwise.yaml
chateval/metrics/protocols/llama_likert.yaml
chateval/metrics/protocols/utils.py
chateval/utils/__init__.py
chateval/utils/download.py
chateval/utils/extract.py
chateval/utils/file_utils.py
chateval/utils/filelock.py
chateval/utils/logging.py
chateval/utils/naming.py
chateval/utils/prompt_utils.py
chateval/utils/py_util.py
chateval/utils/version.py
integration_tests/__init__.py
integration_tests/chateval_class_test.py
integration_tests/gptscore_test.py
integration_tests/metric_test.py
integration_tests/artifacts/__init__.py
integration_tests/artifacts/utils.py
integration_tests/artifacts/yaml_config/__init__.py
integration_tests/artifacts/yaml_config/write_email/__init__.py
scenarios/__init__.py
scenarios/brainstorming/__init__.py
scenarios/brainstorming/brainstorming.py
scenarios/brainstorming/brainstorming_test.py
scenarios/code/__init__.py
scenarios/code/code.py
scenarios/code/code_test.py
scenarios/dialog/__init__.py
scenarios/dialog/dialog.py
scenarios/dialog/dialog_test.py
scenarios/information_extraction/__init__.py
scenarios/information_extraction/information_extraction.py
scenarios/information_extraction/information_extraction_test.py
chateval-0.0.19.dist-info/METADATA
chateval-0.0.19.dist-info/WHEEL
chateval-0.0.19.dist-info/top_level.txt
chateval-0.0.19.dist-info/RECORD
