Metadata-Version: 2.1
Name: chateval
Version: 0.0.19
Summary: Evaluation Framework for Chatbots in Generative AI
Home-page: https://github.com/GAIR-NLP/chateval
Author: GAIR Research Group
License: Apache License
Platform: UNKNOWN
Classifier: Intended Audience :: Developers
Classifier: Topic :: Text Processing
Classifier: Topic :: Scientific/Engineering :: Artificial Intelligence
Classifier: License :: OSI Approved :: Apache Software License
Classifier: Programming Language :: Python :: 3.9
Classifier: Programming Language :: Python :: 3.10
Classifier: Programming Language :: Python :: 3 :: Only
Requires-Dist: nltk (>=3.2)
Requires-Dist: numpy
Requires-Dist: scipy
Requires-Dist: matplotlib
Requires-Dist: scikit-learn
Requires-Dist: pre-commit
Requires-Dist: tqdm
Requires-Dist: openai
Requires-Dist: evaluate
Requires-Dist: rouge-score
Requires-Dist: absl-py
